nuropb/__init__.py
nuropb/contexts/README.md
nuropb/contexts/__init__.py
nuropb/contexts/context_manager.py
nuropb/contexts/context_manager_decorator.py
nuropb/contexts/describe.py
nuropb/contexts/service_handlers.py
nuropb/encodings/README.md
nuropb/encodings/__init__.py
nuropb/encodings/encryption.py
nuropb/encodings/json_serialisation.py
nuropb/encodings/serializor.py
nuropb/interface.py
nuropb/nuropb_api.py
nuropb/rmq_api.py
nuropb/rmq_lib.py
nuropb/rmq_transport.py
nuropb/service_runner.py
nuropb/testing/__init__.py
nuropb/testing/stubs.py
nuropb/utils.py
nuropb-0.1.8.dist-info/LICENSE
nuropb-0.1.8.dist-info/METADATA
nuropb-0.1.8.dist-info/WHEEL
nuropb-0.1.8.dist-info/RECORD
