Metadata-Version: 2.1
Name: nuropb
Version: 0.1.8
Summary: NuroPb - A Distributed Event Driven Service Mesh
Home-page: https://github.com/robertbetts/nuropb
License: Apache-2.0
Keywords: python,asynchrous,api,event,rpc,distributed,edd,ddd,sevice-mesh
Author: Robert Betts
Author-email: robert.betts@genoa.io
Requires-Python: >=3.9,<3.12
Classifier: License :: OSI Approved :: Apache Software License
Classifier: Operating System :: OS Independent
Classifier: Programming Language :: Python :: 3
Classifier: Programming Language :: Python :: 3.9
Classifier: Programming Language :: Python :: 3.10
Classifier: Programming Language :: Python :: 3.11
Provides-Extra: docs
Requires-Dist: etcd3-py (>=0.1.6,<0.2.0)
Requires-Dist: pika (>=1.3.2,<2.0.0)
Requires-Dist: python-dotenv (>=1.0.0,<2.0.0)
Requires-Dist: requests[security] (>=2.31.0,<3.0.0)
Requires-Dist: tornado (>=6.3.3,<7.0.0)
Requires-Dist: types-requests (>=2.31.0.2,<3.0.0.0)
Project-URL: Documentation, https://nuropb.readthedocs.io/en/latest/
Project-URL: Repository, https://github.com/robertbetts/nuropb
